{
	"SN2000I":{
		"name":"SN2000I",
		"aliases":[
			"SN2000I"
		],
		"sources":[
			{
				"name":"Sternberg Astronomical Institute Supernova Light Curve Catalogue",
				"url":"http://dau.itep.ru/sn/node/72",
				"alias":"1",
				"secondary":true
			},
			{
				"name":"VSNET 2001",
				"alias":"2"
			},
			{
				"name":"Asiago Supernova Catalogue",
				"url":"http://graspa.oapd.inaf.it/cgi-bin/sncat.php",
				"alias":"3",
				"secondary":true
			},
			{
				"name":"2012A&A...538A.120L",
				"url":"http://adsabs.harvard.edu/abs/2012A&A...538A.120L",
				"bibcode":"2012A&A...538A.120L",
				"alias":"4"
			},
			{
				"name":"IAUC 7362",
				"url":"http://www.cbat.eps.harvard.edu/iauc/07300/07362.html#Item2",
				"alias":"5"
			},
			{
				"name":"Latest Supernovae",
				"url":"http://www.rochesterastronomy.org/snimages/snredshiftall.html",
				"alias":"6",
				"secondary":true
			}
		],
		"claimedtype":[
			{
				"value":"II",
				"source":"3,4,5,6"
			}
		],
		"comovingdist":[
			{
				"value":"97",
				"source":"D"
			}
		],
		"dec":[
			{
				"value":"+11:53:08.5",
				"source":"3,4,5,6"
			}
		],
		"discover":[
			{
				"value":"2000/2/4",
				"source":"3"
			}
		],
		"discoverdate":[
			{
				"value":"2000/02/04",
				"source":"4,5,6"
			}
		],
		"discoverer":[
			{
				"value":"Puckett et al.",
				"source":"3"
			},
			{
				"value":"Tim Puckett et al.",
				"source":"5,6"
			}
		],
		"galdec":[
			{
				"value":"+11:53:17",
				"source":"3"
			},
			{
				"value":"+11:53:18.1",
				"source":"4"
			}
		],
		"galra":[
			{
				"value":"09:40:42",
				"source":"3"
			},
			{
				"value":"09:40:41.64",
				"source":"4"
			}
		],
		"host":[
			{
				"value":"NGC 2958",
				"source":"3,4,5,6"
			}
		],
		"hvel":[
			{
				"value":"6639",
				"source":"3"
			}
		],
		"lumdist":[
			{
				"value":"99",
				"source":"D"
			}
		],
		"maxabsmag":[
			{
				"value":"-18",
				"source":"D"
			}
		],
		"maxappmag":[
			{
				"value":"16.8",
				"source":"D"
			}
		],
		"maxband":[
			{
				"value":"C",
				"source":"D"
			}
		],
		"maxdate":[
			{
				"value":"2000/02/16",
				"source":"D"
			}
		],
		"ra":[
			{
				"value":"09:40:41.54",
				"source":"3,4,5,6"
			}
		],
		"redshift":[
			{
				"value":"0.022",
				"source":"4"
			},
			{
				"value":"0.021",
				"source":"5,6"
			}
		],
		"photometry":[
			{
				"timeunit":"MJD",
				"time":"51578.17",
				"band":"C",
				"magnitude":"18.6",
				"source":"1,2"
			},
			{
				"timeunit":"MJD",
				"time":"51584.32",
				"band":"B",
				"magnitude":"18.69",
				"source":"1,2"
			},
			{
				"timeunit":"MJD",
				"time":"51584.32",
				"band":"V",
				"magnitude":"17.85",
				"source":"1,2"
			},
			{
				"timeunit":"MJD",
				"time":"51589.5",
				"magnitude":"16.8",
				"source":"5,6"
			},
			{
				"timeunit":"MJD",
				"time":"51590.08",
				"band":"C",
				"magnitude":"16.8",
				"source":"1,2"
			},
			{
				"timeunit":"MJD",
				"time":"51599.24",
				"band":"R",
				"magnitude":"17.3",
				"source":"1,2"
			},
			{
				"timeunit":"MJD",
				"time":"51602.89",
				"band":"C",
				"magnitude":"17.1",
				"source":"1,2"
			},
			{
				"timeunit":"MJD",
				"time":"51611.9",
				"band":"R",
				"magnitude":"17.5",
				"source":"1,2"
			},
			{
				"timeunit":"MJD",
				"time":"51618.91",
				"band":"C",
				"magnitude":"18.2",
				"source":"1,2"
			}
		]
	}
}