{
	"SN2002ev":{
		"name":"SN2002ev",
		"aliases":[
			"SN2002ev"
		],
		"sources":[
			{
				"name":"Sternberg Astronomical Institute Supernova Light Curve Catalogue",
				"url":"http://dau.itep.ru/sn/node/72",
				"alias":"1",
				"secondary":true
			},
			{
				"name":"VSNET Oct2003",
				"alias":"2"
			},
			{
				"name":"Asiago Supernova Catalogue",
				"url":"http://graspa.oapd.inaf.it/cgi-bin/sncat.php",
				"alias":"3",
				"secondary":true
			},
			{
				"name":"IAUC 7964",
				"url":"http://www.cbat.eps.harvard.edu/iauc/07900/07964.html#Item1",
				"alias":"4"
			},
			{
				"name":"Latest Supernovae",
				"url":"http://www.rochesterastronomy.org/snimages/snredshiftall.html",
				"alias":"5",
				"secondary":true
			},
			{
				"name":"2012A&A...538A.120L",
				"url":"http://adsabs.harvard.edu/abs/2012A&A...538A.120L",
				"bibcode":"2012A&A...538A.120L",
				"alias":"6"
			}
		],
		"claimedtype":[
			{
				"value":"II",
				"source":"3,4,5"
			}
		],
		"discoverday":[
			{
				"value":"24",
				"source":"3,4,5"
			}
		],
		"discoverer":[
			{
				"value":"Wood-Vasey et al.",
				"source":"3"
			},
			{
				"value":"Nearby Supernova Factory",
				"source":"4,5"
			}
		],
		"discovermonth":[
			{
				"value":"8",
				"source":"3,4,5"
			}
		],
		"discoveryear":[
			{
				"value":"2002",
				"source":"1,3,4,5"
			}
		],
		"galdec":[
			{
				"value":"-01:48:14",
				"source":"3"
			}
		],
		"galra":[
			{
				"value":"20:23:00",
				"source":"3"
			}
		],
		"host":[
			{
				"value":"A202300-0148",
				"source":"3"
			}
		],
		"maxappmag":[
			{
				"value":"18.7",
				"source":"D"
			}
		],
		"maxday":[
			{
				"value":"31",
				"source":"D"
			}
		],
		"maxmonth":[
			{
				"value":"8",
				"source":"D"
			}
		],
		"maxyear":[
			{
				"value":"2002",
				"source":"D"
			}
		],
		"sndec":[
			{
				"value":"-01:48:14.6",
				"source":"3,4,5"
			}
		],
		"snra":[
			{
				"value":"20:23:00.85",
				"source":"3,4,5"
			}
		],
		"photometry":[
			{
				"timeunit":"MJD",
				"time":"52501.0",
				"band":"C",
				"magnitude":"20.2",
				"source":"1,2"
			},
			{
				"timeunit":"MJD",
				"time":"52509.5",
				"magnitude":"20.5",
				"source":"4,5"
			},
			{
				"timeunit":"MJD",
				"time":"52510.26",
				"band":"C",
				"magnitude":"18.8",
				"source":"1,2"
			},
			{
				"timeunit":"MJD",
				"time":"52510.31",
				"band":"C",
				"magnitude":"18.8",
				"source":"1,2"
			},
			{
				"timeunit":"MJD",
				"time":"52511.0",
				"band":"C",
				"magnitude":"19.1",
				"source":"1,2"
			},
			{
				"timeunit":"MJD",
				"time":"52517.0",
				"band":"C",
				"magnitude":"18.7",
				"source":"1,2"
			},
			{
				"timeunit":"MJD",
				"time":"52520.0",
				"band":"C",
				"magnitude":"18.7",
				"source":"1,2"
			}
		]
	}
}