{
	"SN2002az":{
		"name":"SN2002az",
		"aliases":[
			"SN2002az"
		],
		"sources":[
			{
				"name":"Asiago Supernova Catalogue",
				"url":"http://graspa.oapd.inaf.it/cgi-bin/sncat.php",
				"alias":"1",
				"secondary":true
			},
			{
				"name":"IAUC 7833",
				"url":"http://www.cbat.eps.harvard.edu/iauc/07800/07833.html#Item1",
				"alias":"2"
			},
			{
				"name":"Latest Supernovae",
				"url":"http://www.rochesterastronomy.org/snimages/snredshiftall.html",
				"alias":"3",
				"secondary":true
			},
			{
				"name":"2012A&A...538A.120L",
				"url":"http://adsabs.harvard.edu/abs/2012A&A...538A.120L",
				"bibcode":"2012A&A...538A.120L",
				"alias":"4"
			}
		],
		"discoverday":"14",
		"discoverer":[
			{
				"value":"Becker et al. DLS",
				"source":"1"
			},
			{
				"value":"Deep Lense survey",
				"source":"2,3"
			}
		],
		"discovermonth":"2",
		"discoveryear":"2002",
		"galdec":[
			{
				"value":"-04:54:16",
				"source":"1"
			}
		],
		"galra":[
			{
				"value":"10:54:17",
				"source":"1"
			}
		],
		"host":[
			{
				"value":"A105417-0454",
				"source":"1"
			}
		],
		"maxappmag":"22.9",
		"maxday":"13",
		"maxmonth":"2",
		"maxyear":"2002",
		"sndec":[
			{
				"value":"-04:54:16.0",
				"source":"1,2,3"
			}
		],
		"snra":[
			{
				"value":"10:54:17.44",
				"source":"1,2,3"
			}
		],
		"photometry":[
			{
				"timeunit":"MJD",
				"time":"52318.5",
				"abmag":"22.9",
				"source":"2,3"
			}
		]
	}
}