{
	"SNLS-04D3do":{
		"name":"SNLS-04D3do",
		"aliases":[
			"SNLS-04D3do"
		],
		"sources":[
			{
				"name":"2010A&A...523A...7G",
				"url":"http://adsabs.harvard.edu/abs/2010A&A...523A...7G",
				"bibcode":"2010A&A...523A...7G",
				"alias":"1"
			},
			{
				"name":"Paper",
				"url":"http://www.aanda.org/index.php?option=com_article&access=standard&Itemid=129&url2004/04/21",
				"alias":"2"
			},
			{
				"name":"Latest Supernovae",
				"url":"http://www.rochesterastronomy.org/snimages/snredshiftall.html",
				"alias":"3",
				"secondary":true
			},
			{
				"name":"NED-D",
				"url":"http://ned.ipac.caltech.edu/Library/Distances/",
				"alias":"4",
				"secondary":true
			},
			{
				"name":"2010arXiv1006.2112L",
				"url":"http://adsabs.harvard.edu/abs/2010arXiv1006.2112L",
				"bibcode":"2010arXiv1006.2112L",
				"alias":"5"
			},
			{
				"name":"2010ApJ...716..712A",
				"url":"http://adsabs.harvard.edu/abs/2010ApJ...716..712A",
				"bibcode":"2010ApJ...716..712A",
				"alias":"6"
			},
			{
				"name":"2011ApJS..192....1C",
				"url":"http://adsabs.harvard.edu/abs/2011ApJS..192....1C",
				"bibcode":"2011ApJS..192....1C",
				"alias":"7"
			},
			{
				"name":"2009ApJ...700.1097H",
				"url":"http://adsabs.harvard.edu/abs/2009ApJ...700.1097H",
				"bibcode":"2009ApJ...700.1097H",
				"alias":"8"
			},
			{
				"name":"2006A&A...447...31A",
				"url":"http://adsabs.harvard.edu/abs/2006A&A...447...31A",
				"bibcode":"2006A&A...447...31A",
				"alias":"9"
			},
			{
				"name":"2007ApJ...666..694W",
				"url":"http://adsabs.harvard.edu/abs/2007ApJ...666..694W",
				"bibcode":"2007ApJ...666..694W",
				"alias":"10"
			},
			{
				"name":"2009ApJS..185...32K",
				"url":"http://adsabs.harvard.edu/abs/2009ApJS..185...32K",
				"bibcode":"2009ApJS..185...32K",
				"alias":"11"
			},
			{
				"name":"2008ApJ...686..749K",
				"url":"http://adsabs.harvard.edu/abs/2008ApJ...686..749K",
				"bibcode":"2008ApJ...686..749K",
				"alias":"12"
			},
			{
				"name":"2013MNRAS.433.2240G",
				"url":"http://adsabs.harvard.edu/abs/2013MNRAS.433.2240G",
				"bibcode":"2013MNRAS.433.2240G",
				"alias":"13"
			}
		],
		"claimedtype":[
			{
				"value":"Ia?",
				"source":"1"
			},
			{
				"value":"Ia",
				"source":"2,3"
			}
		],
		"discoverday":"21",
		"discoverer":[
			{
				"value":"Supernova Legacy Project",
				"source":"2,3"
			}
		],
		"discovermonth":"4",
		"discoveryear":"2004",
		"ebv":[
			{
				"value":"0.009",
				"source":"1"
			}
		],
		"hvel":[
			{
				"value":"130000",
				"source":"D"
			}
		],
		"lumdist":[
			{
				"value":"2070",
				"error":"60",
				"source":"7,4"
			}
		],
		"maxabsmag":"-18.9",
		"maxappmag":"22.69",
		"maxday":"14",
		"maxmonth":"4",
		"maxyear":"2004",
		"redshift":[
			{
				"value":"0.61",
				"source":"1,2,3"
			}
		],
		"sndec":[
			{
				"value":"+52:16:03.190",
				"source":"1"
			},
			{
				"value":"+52:16:03.36",
				"source":"2,3"
			}
		],
		"snra":[
			{
				"value":"14:17:46.082",
				"source":"1"
			},
			{
				"value":"14:17:46.113",
				"source":"2,3"
			}
		],
		"photometry":[
			{
				"timeunit":"MJD",
				"time":"53083.53",
				"band":"i",
				"abmag":"25.429",
				"aberr":"0.34135",
				"source":"1"
			},
			{
				"timeunit":"MJD",
				"time":"53083.58",
				"band":"r",
				"abmag":"26.239",
				"aberr":"0.34954",
				"source":"1"
			},
			{
				"timeunit":"MJD",
				"time":"53094.54",
				"band":"i",
				"abmag":"24.39",
				"aberr":"0.11539",
				"source":"1"
			},
			{
				"timeunit":"MJD",
				"time":"53094.59",
				"band":"r",
				"abmag":"24.774",
				"aberr":"0.12024",
				"source":"1"
			},
			{
				"timeunit":"MJD",
				"time":"53094.61",
				"band":"z",
				"abmag":"24.121",
				"aberr":"0.34692",
				"source":"1"
			},
			{
				"timeunit":"MJD",
				"time":"53109.49",
				"band":"i",
				"abmag":"22.686",
				"aberr":"0.030939",
				"source":"1"
			},
			{
				"timeunit":"MJD",
				"time":"53109.54",
				"band":"r",
				"abmag":"22.934",
				"aberr":"0.024084",
				"source":"1"
			},
			{
				"timeunit":"MJD",
				"time":"53109.58",
				"band":"g",
				"abmag":"24.124",
				"aberr":"0.072856",
				"source":"1"
			},
			{
				"timeunit":"MJD",
				"time":"53112.53",
				"band":"i",
				"abmag":"22.7",
				"aberr":"0.0434",
				"source":"1"
			},
			{
				"timeunit":"MJD",
				"time":"53115.5",
				"abmag":"25.0",
				"source":"2,3"
			},
			{
				"timeunit":"MJD",
				"time":"53116.50",
				"band":"i",
				"abmag":"22.745",
				"aberr":"0.035745",
				"source":"1"
			},
			{
				"timeunit":"MJD",
				"time":"53117.44",
				"band":"i",
				"abmag":"22.731",
				"aberr":"0.046767",
				"source":"1"
			},
			{
				"timeunit":"MJD",
				"time":"53117.46",
				"band":"r",
				"abmag":"23.113",
				"aberr":"0.022168",
				"source":"1"
			},
			{
				"timeunit":"MJD",
				"time":"53117.48",
				"band":"g",
				"abmag":"24.728",
				"aberr":"0.059312",
				"source":"1"
			},
			{
				"timeunit":"MJD",
				"time":"53121.41",
				"band":"r",
				"abmag":"23.245",
				"aberr":"0.018992",
				"source":"1"
			},
			{
				"timeunit":"MJD",
				"time":"53121.49",
				"band":"i",
				"abmag":"22.84",
				"aberr":"0.048397",
				"source":"1"
			},
			{
				"timeunit":"MJD",
				"time":"53121.51",
				"band":"g",
				"abmag":"25.131",
				"aberr":"0.091051",
				"source":"1"
			},
			{
				"timeunit":"MJD",
				"time":"53123.41",
				"band":"i",
				"abmag":"22.852",
				"aberr":"0.043531",
				"source":"1"
			},
			{
				"timeunit":"MJD",
				"time":"53123.45",
				"band":"r",
				"abmag":"23.379",
				"aberr":"0.031302",
				"source":"1"
			},
			{
				"timeunit":"MJD",
				"time":"53123.49",
				"band":"z",
				"abmag":"22.785",
				"aberr":"0.069173",
				"source":"1"
			},
			{
				"timeunit":"MJD",
				"time":"53134.28",
				"band":"i",
				"abmag":"23.4",
				"aberr":"0.0766",
				"source":"1"
			},
			{
				"timeunit":"MJD",
				"time":"53134.34",
				"band":"r",
				"abmag":"24.291",
				"aberr":"0.050649",
				"source":"1"
			},
			{
				"timeunit":"MJD",
				"time":"53134.38",
				"band":"z",
				"abmag":"23.733",
				"aberr":"0.18866",
				"source":"1"
			},
			{
				"timeunit":"MJD",
				"time":"53138.41",
				"band":"i",
				"abmag":"23.838",
				"aberr":"0.10426",
				"source":"1"
			},
			{
				"timeunit":"MJD",
				"time":"53138.43",
				"band":"r",
				"abmag":"24.79",
				"aberr":"0.09146",
				"source":"1"
			},
			{
				"timeunit":"MJD",
				"time":"53138.46",
				"band":"g",
				"abmag":"27.297",
				"aberr":"0.59549",
				"source":"1"
			},
			{
				"timeunit":"MJD",
				"time":"53146.43",
				"band":"i",
				"abmag":"24.144",
				"aberr":"0.14479",
				"source":"1"
			},
			{
				"timeunit":"MJD",
				"time":"53146.46",
				"band":"r",
				"abmag":"25.217",
				"aberr":"0.14926",
				"source":"1"
			},
			{
				"timeunit":"MJD",
				"time":"53146.49",
				"band":"g",
				"abmag":"27.078",
				"aberr":"0.481",
				"source":"1"
			},
			{
				"timeunit":"MJD",
				"time":"53149.31",
				"band":"r",
				"abmag":"25.434",
				"aberr":"0.1297",
				"source":"1"
			},
			{
				"timeunit":"MJD",
				"time":"53149.33",
				"band":"g",
				"abmag":"27.714",
				"aberr":"0.60331",
				"source":"1"
			},
			{
				"timeunit":"MJD",
				"time":"53151.33",
				"band":"z",
				"abmag":"24.095",
				"aberr":"0.2226",
				"source":"1"
			},
			{
				"timeunit":"MJD",
				"time":"53151.38",
				"band":"i",
				"abmag":"24.394",
				"aberr":"0.20588",
				"source":"1"
			},
			{
				"timeunit":"MJD",
				"time":"53151.45",
				"band":"r",
				"abmag":"26.056",
				"aberr":"0.41906",
				"source":"1"
			},
			{
				"timeunit":"MJD",
				"time":"53165.33",
				"band":"i",
				"abmag":"25.436",
				"aberr":"0.37658",
				"source":"1"
			},
			{
				"timeunit":"MJD",
				"time":"53165.39",
				"band":"r",
				"abmag":"26.336",
				"aberr":"0.27693",
				"source":"1"
			},
			{
				"timeunit":"MJD",
				"time":"53169.35",
				"band":"i",
				"abmag":"24.912",
				"aberr":"0.21988",
				"source":"1"
			},
			{
				"timeunit":"MJD",
				"time":"53169.38",
				"band":"r",
				"abmag":"25.922",
				"aberr":"0.30098",
				"source":"1"
			},
			{
				"timeunit":"MJD",
				"time":"53169.42",
				"band":"z",
				"abmag":"24.035",
				"aberr":"0.3382",
				"source":"1"
			},
			{
				"timeunit":"MJD",
				"time":"53175.33",
				"band":"i",
				"abmag":"24.835",
				"aberr":"0.21261",
				"source":"1"
			},
			{
				"timeunit":"MJD",
				"time":"53175.38",
				"band":"g",
				"abmag":"27.153",
				"aberr":"0.51319",
				"source":"1"
			},
			{
				"timeunit":"MJD",
				"time":"53177.38",
				"band":"z",
				"abmag":"24.468",
				"aberr":"0.27315",
				"source":"1"
			},
			{
				"timeunit":"MJD",
				"time":"53178.31",
				"band":"i",
				"abmag":"25.13",
				"aberr":"0.2533",
				"source":"1"
			},
			{
				"timeunit":"MJD",
				"time":"53178.35",
				"band":"r",
				"abmag":"26.446",
				"aberr":"0.31236",
				"source":"1"
			},
			{
				"timeunit":"MJD",
				"time":"53182.36",
				"band":"z",
				"abmag":"24.812",
				"aberr":"0.33667",
				"source":"1"
			},
			{
				"timeunit":"MJD",
				"time":"53193.34",
				"band":"i",
				"abmag":"25.624",
				"aberr":"0.34444",
				"source":"1"
			},
			{
				"timeunit":"MJD",
				"time":"53193.38",
				"band":"r",
				"abmag":"26.156",
				"aberr":"0.44298",
				"source":"1"
			},
			{
				"timeunit":"MJD",
				"time":"53197.34",
				"band":"r",
				"abmag":"25.999",
				"aberr":"0.26093",
				"source":"1"
			},
			{
				"timeunit":"MJD",
				"time":"53198.30",
				"band":"r",
				"abmag":"26.617",
				"aberr":"0.49367",
				"source":"1"
			},
			{
				"timeunit":"MJD",
				"time":"53202.29",
				"band":"i",
				"abmag":"25.35",
				"aberr":"0.27763",
				"source":"1"
			},
			{
				"timeunit":"MJD",
				"time":"53204.30",
				"band":"z",
				"abmag":"24.812",
				"aberr":"0.32253",
				"source":"1"
			},
			{
				"timeunit":"MJD",
				"time":"53204.35",
				"band":"r",
				"abmag":"26.917",
				"aberr":"0.55013",
				"source":"1"
			},
			{
				"timeunit":"MJD",
				"time":"53226.27",
				"band":"i",
				"abmag":"25.717",
				"aberr":"0.5598",
				"source":"1"
			},
			{
				"timeunit":"MJD",
				"time":"53386.65",
				"band":"r",
				"abmag":"27.016",
				"aberr":"0.58523",
				"source":"1"
			},
			{
				"timeunit":"MJD",
				"time":"53409.63",
				"band":"i",
				"abmag":"26.728",
				"aberr":"0.68308",
				"source":"1"
			},
			{
				"timeunit":"MJD",
				"time":"53411.60",
				"band":"r",
				"abmag":"27.252",
				"aberr":"0.59787",
				"source":"1"
			},
			{
				"timeunit":"MJD",
				"time":"53415.55",
				"band":"i",
				"abmag":"25.796",
				"aberr":"0.53324",
				"source":"1"
			},
			{
				"timeunit":"MJD",
				"time":"53419.60",
				"band":"i",
				"abmag":"25.865",
				"aberr":"0.43554",
				"source":"1"
			}
		]
	}
}